distrunner/__init__.py
distrunner/distrunner.py
distrunner/dr_test.py
distrunner-1.4.1.dist-info/LICENSE.md
distrunner-1.4.1.dist-info/METADATA
distrunner-1.4.1.dist-info/WHEEL
distrunner-1.4.1.dist-info/top_level.txt
distrunner-1.4.1.dist-info/RECORD
