Metadata-Version: 2.1
Name: distrunner
Version: 1.4.1
Summary: This library allows for the easy construction and management of Dask clusters.
Home-page: https://gitlab.com/crossref/labs/distrunner
Author: Martin Paul Eve
Author-email: meve@crossref.org
Maintainer-email: Martin Paul Eve <meve@crossref.org>
License: Copyright &copy; 2023 Crossref
Project-URL: homepage, https://labs.crossref.org
Project-URL: documentation, https://labs.crossref.org
Project-URL: repository, https://gitlab.com/crossref/labs/distrunner
Project-URL: changelog, https://gitlab.com/crossref/labs/distrunner/-/blob/main/CHANGELOG.md
Keywords: distributed computing
Classifier: Development Status :: 4 - Beta
Classifier: Programming Language :: Python
Requires-Python: >=3.8
License-File: LICENSE.md
Requires-Dist: dask-cloudprovider[aws] ==2022.10.0
Requires-Dist: pandas
Requires-Dist: numpy
Requires-Dist: cryptography
Requires-Dist: botocore ~=1.27.59
Requires-Dist: distributed ~=2023.3.0
Requires-Dist: dask ~=2023.3.0
Requires-Dist: GitPython
Requires-Dist: requests
